magmalab/__init__.py
magmalab/lava.py
magmalab/_core/__init__.py
magmalab/_core/drill.py
magmalab/_core/metrics.py
magmalab/_core/stats.py
magmalab/_core/utils.py
magmalab/_data/__init__.py
magmalab/_data/mine.csv
magmalab/_engine/__init__.py
magmalab/_engine/correlations.py
magmalab/_engine/diagnostics.py
magmalab/_engine/geo3d.py
magmalab/_engine/geochemistry.py
magmalab/_engine/plots.py
magmalab-0.0.7.dist-info/METADATA
magmalab-0.0.7.dist-info/WHEEL
magmalab-0.0.7.dist-info/licenses/LICENSE
magmalab-0.0.7.dist-info/RECORD
